README.md
setup.py
paleocirc/__init__.py
paleocirc/circolari.py
paleocirc/circolariasync.py
paleocirc.egg-info/PKG-INFO
paleocirc.egg-info/SOURCES.txt
paleocirc.egg-info/dependency_links.txt
paleocirc.egg-info/requires.txt
paleocirc.egg-info/top_level.txt