Metadata-Version: 2.1
Name: paleocirc
Version: 1.1.2
Summary: API web scraping per ottenere circolari dal sito dell'I.T.I.S. Paleocapa di Bergamo
Home-page: https://github.com/xFranciB/paleocirc
Author: xFranciB
License: MIT
Download-URL: https://github.com/xFranciB/paleocirc/archive/refs/tags/v1.1.2.tar.gz
Platform: UNKNOWN
